cmtutils/__init__.py
cmtutils/cmtutils.py
cmtutils/config.py
cmtutils/defaults.cfg
cmtutils/nipsy.py
cmtutils/plot.py
cmtutils-0.1.2.dist-info/METADATA
cmtutils-0.1.2.dist-info/WHEEL
cmtutils-0.1.2.dist-info/dependency_links.txt
cmtutils-0.1.2.dist-info/entry_points.txt
cmtutils-0.1.2.dist-info/top_level.txt
cmtutils-0.1.2.dist-info/RECORD
