Metadata-Version: 2.1
Name: cmtutils
Version: 0.1.2
Summary: Package of utility files for working with CMT 2.0 from NeurIPS 2014.
Home-page: https://github.com/lawrennd/cmtutils
Author: Neil D. Lawrence
Author-email: lawrennd@gmail.com
License: MIT
Platform: UNKNOWN
Classifier: License :: OSI Approved :: MIT License
Classifier: Programming Language :: Python
Classifier: Programming Language :: Python :: 3
Classifier: Programming Language :: Python :: 3.6
Classifier: Programming Language :: Python :: Implementation :: CPython
Classifier: Programming Language :: Python :: Implementation :: PyPy
Requires-Python: >=3.6.0
Requires-Dist: openpyxl
Requires-Dist: pods
Requires-Dist: pandas
Requires-Dist: lxml
Requires-Dist: googoal
